psd_covariance/__init__.py
psd_covariance/eigenvalue_cleaning.py
psd_covariance/posterior_mean.py
psd_covariance/shrinkage_methods.py
psd_covariance/utils.py
psd_covariance-1.0.3.dist-info/licenses/LICENSE
psd_covariance-1.0.3.dist-info/METADATA
psd_covariance-1.0.3.dist-info/WHEEL
psd_covariance-1.0.3.dist-info/top_level.txt
psd_covariance-1.0.3.dist-info/RECORD
