Metadata-Version: 2.4
Name: psd-covariance
Version: 1.0.3
Summary: Computes several covariance matrix estimators that ensure positive semi-definiteness (PSD).
Author: Jesper Cremers
Author-email: Jesper.Cremers@vub.be
License: MIT
Classifier: Programming Language :: Python :: 3
Classifier: License :: OSI Approved :: MIT License
Classifier: Operating System :: OS Independent
Requires-Python: >=3.7
License-File: LICENSE
Requires-Dist: numpy
Requires-Dist: scipy
Requires-Dist: joblib
Requires-Dist: scikit-learn
Requires-Dist: pandas
Dynamic: author
Dynamic: author-email
Dynamic: classifier
Dynamic: description
Dynamic: description-content-type
Dynamic: license
Dynamic: license-file
Dynamic: requires-dist
Dynamic: requires-python
Dynamic: summary
